tololib/__init__.py
tololib/client.py
tololib/command_value_handler.py
tololib/const.py
tololib/device_simulator.py
tololib/enums.py
tololib/message.py
tololib/py.typed
tololib/state.py
tololib/cli/__init__.py
tololib/cli/common.py
tololib/cli/device_simulator.py
tololib/cli/discover.py
tololib/cli/get_settings.py
tololib/cli/get_status.py
tololib/cli/main.py
tololib-1.2.1.dist-info/LICENSE.md
tololib-1.2.1.dist-info/METADATA
tololib-1.2.1.dist-info/WHEEL
tololib-1.2.1.dist-info/entry_points.txt
tololib-1.2.1.dist-info/top_level.txt
tololib-1.2.1.dist-info/RECORD
