Metadata-Version: 2.2
Name: tololib
Version: 1.2.1
Summary: Python Library and Command Line Interface for Communicating with TOLO Steam Generators
Home-page: https://gitlab.com/MatthiasLohr/tololib
Author: Matthias Lohr
Author-email: mail@mlohr.com
License: MIT
Project-URL: Documentation, https://gitlab.com/MatthiasLohr/tololib/wikis
Project-URL: Source, https://gitlab.com/MatthiasLohr/tololib
Project-URL: Tracker, https://gitlab.com/MatthiasLohr/tololib/issues
Classifier: Development Status :: 5 - Production/Stable
Classifier: Environment :: Console
Classifier: Intended Audience :: Developers
Classifier: License :: OSI Approved :: MIT License
Classifier: Operating System :: OS Independent
Classifier: Programming Language :: Python :: 3.7
Classifier: Programming Language :: Python :: 3.8
Classifier: Programming Language :: Python :: 3.9
Classifier: Programming Language :: Python :: 3.10
Classifier: Programming Language :: Python :: 3.11
Classifier: Programming Language :: Python :: 3.12
Classifier: Programming Language :: Python :: 3.13
Classifier: Topic :: Home Automation
Classifier: Typing :: Typed
Requires-Python: >=3.7, <4
License-File: LICENSE.md
Dynamic: author
Dynamic: author-email
Dynamic: classifier
Dynamic: description
Dynamic: description-content-type
Dynamic: home-page
Dynamic: license
Dynamic: project-url
Dynamic: requires-python
Dynamic: summary
